[
    {
        "name": "新たな戦い 響",
        "code": "SG/W70-001",
        "rarity": "RR",
        "expansion": "Senki Zesshou Symphogear AXZ",
        "side": "W",
        "type": "Character",
        "color": "YELLOW",
        "level": "1",
        "cost": "0",
        "trigger": [],
        "power": "3000",
        "soul": 1,
        "flavor_text": "-",
        "ability": [
            "【C】During your turn, this card gets +2000 Power.",
            "【A】When this card attacks, choose 1 of your other Character, during this turn, it gets +1500 Power.",
            "【A】RESONANCE [Reveal 1 「新たな戦い 切歌」 from Hand] At the beginning of your Climax Phase, you may pay the cost. If you did, during this turn, this card gets +1 Soul."
        ],
        "attributes": [
            "Music 《音楽》"
        ],
        "set": "SG",
        "release": "W70",
        "sid": "001",
        "image": "https://images.littleakiba.com/tcg/card53225-large.jpg"
    },
    {
        "name": "“Alchemic Gold”響",
        "code": "SG/W70-002",
        "rarity": "RR",
        "expansion": "Senki Zesshou Symphogear AXZ",
        "side": "W",
        "type": "Character",
        "color": "YELLOW",
        "level": "3",
        "cost": "2",
        "trigger": [
            "SOUL"
        ],
        "power": "10000",
        "soul": 2,
        "flavor_text": "-",
        "ability": [
            "【A】When this card is placed on Stage from Hand, look at up to 3 cards from your top Deck, choose up to 1 card, add it to Hand, place the remaining cards into Waiting Room.",
            "【A】【CXCOMBO】[(4)] When this card attacks, if 「TESTAMENT」 is in your Climax Slot, and you have 4 or more other 《音楽》 Character, you may pay the cost. If you did, deal 1 Damage to opponent, during this turn, this card gains the following Ability. 『【A】When this card's battle opponent becomes REVERSE, perform the following Action 2 times. 『Deal 1 Damage to opponent.』』(Damage can be cancelled)"
        ],
        "attributes": [
            "Music 《音楽》"
        ],
        "set": "SG",
        "release": "W70",
        "sid": "002",
        "image": "https://images.littleakiba.com/tcg/card53227-large.jpg"
    },
    {
        "name": "緊急参戦 響",
        "code": "SG/W70-003",
        "rarity": "R",
        "expansion": "Senki Zesshou Symphogear AXZ",
        "side": "W",
        "type": "Character",
        "color": "YELLOW",
        "level": "0",
        "cost": "0",
        "trigger": [],
        "power": "2000",
        "soul": 1,
        "flavor_text": "-",
        "ability": [
            "【S】CONCENTRATION ［(1) REST this card］ Flip the top 4 cards of your Deck, place them into Waiting Room. For each Climax among those cards, choose up to 1 Character from your Waiting Room, return it to Hand."
        ],
        "attributes": [
            "Music 《音楽》"
        ],
        "set": "SG",
        "release": "W70",
        "sid": "003",
        "image": "https://images.littleakiba.com/tcg/card53229-large.jpg"
    },
    {
        "name": "呼び戻す声 未来",
        "code": "SG/W70-004",
        "rarity": "R",
        "expansion": "Senki Zesshou Symphogear AXZ",
        "side": "W",
        "type": "Character",
        "color": "YELLOW",
        "level": "1",
        "cost": "0",
        "trigger": [],
        "power": "4500",
        "soul": 1,
        "flavor_text": "-",
        "ability": [
            "【A】When this card is placed on Stage from Hand, during this turn, this card gets +1500 Power.",
            "【A】[(1) Put 1 of your Character with 「響」 or 「未来」 in its name in STAND to REST] During the turn when this card is placed on Stage from Hand, when this card's battle opponent becomes REVERSE, you may pay the cost. If you did, search your Deck for up to 1 Character with 「響」 or 「未来」 in its name and show it to opponent, add it to Hand, shuffle your Deck afterwards."
        ],
        "attributes": [
            "Music 《音楽》"
        ],
        "set": "SG",
        "release": "W70",
        "sid": "004",
        "image": "https://images.littleakiba.com/tcg/card53230-large.jpg"
    },
    {
        "name": "みんなのアームドギア 響",
        "code": "SG/W70-005",
        "rarity": "R",
        "expansion": "Senki Zesshou Symphogear AXZ",
        "side": "W",
        "type": "Character",
        "color": "YELLOW",
        "level": "1",
        "cost": "1",
        "trigger": [
            "SOUL"
        ],
        "power": "4000",
        "soul": 1,
        "flavor_text": "-",
        "ability": [
            "【C】SUPPORT All your 《音楽》 Character in front of this card gets +X Power. X is equal to that Character's Level x500.",
            "【S】[REST this card] Choose 1 of your 《音楽》 Character, during this turn, it gets +1000 Power.",
            "【S】[REST this card] If you have each of 1 Character that has 「翼」「クリス」「マリア」「切歌」「調」 in its name, choose 1 of your 「“Alchemic Gold”響」, during this turn, it gets +5000 Power."
        ],
        "attributes": [
            "Music 《音楽》"
        ],
        "set": "SG",
        "release": "W70",
        "sid": "005",
        "image": "https://images.littleakiba.com/tcg/card53232-large.jpg"
    },
    {
        "name": "繋ぐ力 響",
        "code": "SG/W70-006",
        "rarity": "R",
        "expansion": "Senki Zesshou Symphogear AXZ",
        "side": "W",
        "type": "Character",
        "color": "YELLOW",
        "level": "2",
        "cost": "1",
        "trigger": [
            "SOUL"
        ],
        "power": "2500",
        "soul": 1,
        "flavor_text": "-",
        "ability": [
            "【A】[(2) Place 1 of your Character from Stage into Waiting Room] When you use this card's 『ASSIST』, you may pay the cost. If you did, choose 1 opponent's Character with Level higher than opponent's Level, place it into Waiting Room.",
            "【S】【COUNTER】 ASSIST 2500 Level 2 ［(1) Place this card from Hand into Waiting Room］ (Choose 1 of your Characters being Front Attacked, during that turn, it gets ＋2500 Power)"
        ],
        "attributes": [
            "Music 《音楽》"
        ],
        "set": "SG",
        "release": "W70",
        "sid": "006",
        "image": "https://images.littleakiba.com/tcg/card53234-large.jpg"
    },
    {
        "name": "二人の時間 響＆未来",
        "code": "SG/W70-007",
        "rarity": "R",
        "expansion": "Senki Zesshou Symphogear AXZ",
        "side": "W",
        "type": "Character",
        "color": "YELLOW",
        "level": "3",
        "cost": "2",
        "trigger": [
            "SOUL"
        ],
        "power": "10000",
        "soul": 2,
        "flavor_text": "-",
        "ability": [
            "【C】If your Waiting Room has 2 or less Climax, this card gets -1 Level in your Hand.",
            "【A】When this card is placed on Stage from Hand, you may place the top card of your Clock into Waiting Room."
        ],
        "attributes": [
            "Music 《音楽》"
        ],
        "set": "SG",
        "release": "W70",
        "sid": "007",
        "image": "https://images.littleakiba.com/tcg/card53236-large.jpg"
    },
    {
        "name": "それぞれの正義 響",
        "code": "SG/W70-008",
        "rarity": "U",
        "expansion": "Senki Zesshou Symphogear AXZ",
        "side": "W",
        "type": "Character",
        "color": "YELLOW",
        "level": "0",
        "cost": "0",
        "trigger": [],
        "power": "1500",
        "soul": 1,
        "flavor_text": "-",
        "ability": [
            "【A】[Place 1 《音楽》 Character from Hand into Waiting Room] When this card is placed on Stage from Hand, you may pay the cost. If you did, choose 1 「新たな戦い 響」 or 「新たな戦い 切歌」 from your Waiting Room, return it to Hand.",
            "【A】When this card attacks, choose 1 of your 《音楽》 Character, during this turn, it gets +1500 Power."
        ],
        "attributes": [
            "Music 《音楽》"
        ],
        "set": "SG",
        "release": "W70",
        "sid": "008",
        "image": "https://images.littleakiba.com/tcg/card53238-large.jpg"
    },
    {
        "name": "終わりなき闘争 響",
        "code": "SG/W70-009",
        "rarity": "U",
        "expansion": "Senki Zesshou Symphogear AXZ",
        "side": "W",
        "type": "Character",
        "color": "YELLOW",
        "level": "0",
        "cost": "0",
        "trigger": [],
        "power": "1500",
        "soul": 1,
        "flavor_text": "-",
        "ability": [
            "【C】All your other 《音楽》 Character gets +500 Power.",
            "【A】When this card is placed on Stage from Hand, place 2 cards from your top Deck into Waiting Room. If there is a Climax among those cards, choose 1 of your Character, during this turn, it gets +1500 Power."
        ],
        "attributes": [
            "Music 《音楽》"
        ],
        "set": "SG",
        "release": "W70",
        "sid": "009",
        "image": "https://images.littleakiba.com/tcg/card53239-large.jpg"
    },
    {
        "name": "錬金術師との対峙 響",
        "code": "SG/W70-010",
        "rarity": "U",
        "expansion": "Senki Zesshou Symphogear AXZ",
        "side": "W",
        "type": "Character",
        "color": "YELLOW",
        "level": "0",
        "cost": "0",
        "trigger": [],
        "power": "1500",
        "soul": 1,
        "flavor_text": "-",
        "ability": [
            "【A】When this card is placed on Stage from Hand, reveal the top card of your Deck. If that card is a 《音楽》 Character, add it to Hand, choose 1 card from your Hand, place it into Waiting Room. (If not, return revealed card to its original position)",
            "【A】When this card is placed on Stage from Hand, place 2 cards from your top Deck into Waiting Room. If there is a Climax among those cards, during this turn, this card gets +3000 Power."
        ],
        "attributes": [
            "Music 《音楽》"
        ],
        "set": "SG",
        "release": "W70",
        "sid": "010",
        "image": "https://images.littleakiba.com/tcg/card53241-large.jpg"
    },
    {
        "name": "差し伸べた手 響",
        "code": "SG/W70-011",
        "rarity": "U",
        "expansion": "Senki Zesshou Symphogear AXZ",
        "side": "W",
        "type": "Character",
        "color": "YELLOW",
        "level": "0",
        "cost": "0",
        "trigger": [],
        "power": "2000",
        "soul": 1,
        "flavor_text": "-",
        "ability": [
            "【A】At the beginning of opponent's Draw Phase, reveal the top card of your Deck. If that card is Level 1 or higher, you may return this card to Hand. (Climax is considered Level 0. Return revealed card to its original position)"
        ],
        "attributes": [
            "Music 《音楽》"
        ],
        "set": "SG",
        "release": "W70",
        "sid": "011",
        "image": "https://images.littleakiba.com/tcg/card53242-large.jpg"
    },
    {
        "name": "絆のユニゾン 響",
        "code": "SG/W70-012",
        "rarity": "U",
        "expansion": "Senki Zesshou Symphogear AXZ",
        "side": "W",
        "type": "Character",
        "color": "YELLOW",
        "level": "1",
        "cost": "0",
        "trigger": [],
        "power": "5500",
        "soul": 1,
        "flavor_text": "-",
        "ability": [
            "【C】If you have no other Character with 「切歌」 in its name, this card cannot STAND during your Standby Phase.",
            "【A】【CXCOMBO】[(1)] When this card attacks, if 「必愛デュオシャウト」 is in your Climax Slot, you may pay the cost. If you did, during this turn, all your other Character gains the following Ability. 『【A】When this card's battle opponent becomes REVERSE, you may choose 1 Character from your Waiting Room, return it to Hand.』"
        ],
        "attributes": [
            "Music 《音楽》"
        ],
        "set": "SG",
        "release": "W70",
        "sid": "012",
        "image": "https://images.littleakiba.com/tcg/card53243-large.jpg"
    },
    {
        "name": "統制局長 アダム",
        "code": "SG/W70-013",
        "rarity": "U",
        "expansion": "Senki Zesshou Symphogear AXZ",
        "side": "W",
        "type": "Character",
        "color": "YELLOW",
        "level": "2",
        "cost": "1",
        "trigger": [
            "SOUL"
        ],
        "power": "7000",
        "soul": 1,
        "flavor_text": "-",
        "ability": [
            "【C】If this card is on Stage, this card loses 《服》.",
            "【A】When this card is placed on Stage from Hand, if you have other 《錬金術》 Character, during this turn, this card gets +4000 Power.",
            "【A】【CXCOMBO】When this card attacks, if 「黄金錬成」 is in your Climax Slot, choose 1 of your 「神力顕現　ティキ」, during this turn, it gains the following Ability. 『【A】When this card's battle opponent becomes REVERSE, you may choose 1 Character from your Waiting Room, return it to Hand.』Then, you may choose 1 of your other 《錬金術》 Character, place it into Waiting Room. If you did, choose 1 of your 「神力顕現 ティキ」, during this turn, it gets +5000 Power."
        ],
        "attributes": [
            "Alchemy 《錬金術》",
            "Clothes 《服》"
        ],
        "set": "SG",
        "release": "W70",
        "sid": "013",
        "image": "https://images.littleakiba.com/tcg/card53244-large.jpg"
    },
    {
        "name": "課題の約束 未来",
        "code": "SG/W70-014",
        "rarity": "C",
        "expansion": "Senki Zesshou Symphogear AXZ",
        "side": "W",
        "type": "Character",
        "color": "YELLOW",
        "level": "0",
        "cost": "0",
        "trigger": [],
        "power": "500",
        "soul": 1,
        "flavor_text": "-",
        "ability": [
            "【A】This Ability can be activated up to 1 time each turn. When your other 「出撃！ 響」 is placed on Stage from Hand, you may choose 1 《音楽》 Character from your Waiting Room, place it into Stock.",
            "【A】BOND／「出撃！ 響」 ［Place 1 card from Hand into Waiting Room］(When this card is played onto Stage, you may pay the cost. If you did, choose 1 「出撃！ 響」 from your Waiting Room, return it to Hand)"
        ],
        "attributes": [
            "Music 《音楽》"
        ],
        "set": "SG",
        "release": "W70",
        "sid": "014",
        "image": "https://images.littleakiba.com/tcg/card53245-large.jpg"
    },
    {
        "name": "再起動 ティキ",
        "code": "SG/W70-015",
        "rarity": "C",
        "expansion": "Senki Zesshou Symphogear AXZ",
        "side": "W",
        "type": "Character",
        "color": "YELLOW",
        "level": "0",
        "cost": "0",
        "trigger": [],
        "power": "1000",
        "soul": 1,
        "flavor_text": "-",
        "ability": [
            "【C】SUPPORT All your Character in front of this card gets +500 Power.",
            "【A】When a Climax is placed into your Climax Slot, choose 1 of your Character, during this turn, it gets +1000 Power."
        ],
        "attributes": [
            "Alchemy 《錬金術》",
            "Doll 《人形》"
        ],
        "set": "SG",
        "release": "W70",
        "sid": "015",
        "image": "https://images.littleakiba.com/tcg/card53246-large.jpg"
    },
    {
        "name": "神の力 ティキ",
        "code": "SG/W70-016",
        "rarity": "C",
        "expansion": "Senki Zesshou Symphogear AXZ",
        "side": "W",
        "type": "Character",
        "color": "YELLOW",
        "level": "0",
        "cost": "0",
        "trigger": [],
        "power": "1500",
        "soul": 1,
        "flavor_text": "-",
        "ability": [
            "【C】If all your other Character are 《錬金術》, this card gets +1000 Power.",
            "【A】[Place 1 Climax from Hand into Waiting Room] When this card is placed on Stage from Hand, you may pay the cost. If you did, choose 1 《錬金術》 Character from your Waiting Room, return it to Hand."
        ],
        "attributes": [
            "Alchemy 《錬金術》",
            "Doll 《人形》"
        ],
        "set": "SG",
        "release": "W70",
        "sid": "016",
        "image": "https://images.littleakiba.com/tcg/card53247-large.jpg"
    },
    {
        "name": "真の姿 アダム",
        "code": "SG/W70-017",
        "rarity": "C",
        "expansion": "Senki Zesshou Symphogear AXZ",
        "side": "W",
        "type": "Character",
        "color": "YELLOW",
        "level": "0",
        "cost": "0",
        "trigger": [],
        "power": "2000",
        "soul": 1,
        "flavor_text": "-",
        "ability": [
            "【C】If this card is at the Center Slot of Front Row, this card gets +1000 Power.",
            "【A】When this card is placed on Stage from Hand, during this turn, this card gets +1500 Power."
        ],
        "attributes": [
            "Alchemy 《錬金術》",
            "Clothes 《服》"
        ],
        "set": "SG",
        "release": "W70",
        "sid": "017",
        "image": "https://images.littleakiba.com/tcg/card53248-large.jpg"
    },
    {
        "name": "ディバインウェポン アダム",
        "code": "SG/W70-018",
        "rarity": "C",
        "expansion": "Senki Zesshou Symphogear AXZ",
        "side": "W",
        "type": "Character",
        "color": "YELLOW",
        "level": "1",
        "cost": "1",
        "trigger": [
            "SOUL"
        ],
        "power": "1000",
        "soul": 1,
        "flavor_text": "-",
        "ability": [
            "【A】When you use this card's 『ASSIST』, you may choose 1 Character with 「シンフォギア装者との対峙」 in its name, send it to Memory.",
            "【S】【COUNTER】 ASSIST 1500 Level 1 ［(1) Place this card from Hand into Waiting Room］ (Choose 1 of your Characters being Front Attacked, during that turn, it gets +1500 Power)"
        ],
        "attributes": [
            "Alchemy 《錬金術》",
            "Clothes 《服》"
        ],
        "set": "SG",
        "release": "W70",
        "sid": "018",
        "image": "https://images.littleakiba.com/tcg/card53249-large.jpg"
    },
    {
        "name": "神力顕現 ティキ",
        "code": "SG/W70-019",
        "rarity": "C",
        "expansion": "Senki Zesshou Symphogear AXZ",
        "side": "W",
        "type": "Character",
        "color": "YELLOW",
        "level": "2",
        "cost": "1",
        "trigger": [
            "SOUL"
        ],
        "power": "6000",
        "soul": 1,
        "flavor_text": "-",
        "ability": [
            "【C】For each of your other 《錬金術》 Character, this card gets +500 Power.",
            "【C】If you have other 「統制局長 アダム」, this card gains the following Ability. 『【A】When this card's battle opponent becomes REVERSE, you may draw 1 card.』"
        ],
        "attributes": [
            "Alchemy 《錬金術》",
            "Doll 《人形》"
        ],
        "set": "SG",
        "release": "W70",
        "sid": "019",
        "image": "https://images.littleakiba.com/tcg/card53250-large.jpg"
    },
    {
        "name": "もうひとりの少女 未来",
        "code": "SG/W70-020",
        "rarity": "C",
        "expansion": "Senki Zesshou Symphogear AXZ",
        "side": "W",
        "type": "Character",
        "color": "YELLOW",
        "level": "2",
        "cost": "1",
        "trigger": [
            "SOUL"
        ],
        "power": "7000",
        "soul": 1,
        "flavor_text": "-",
        "ability": [
            "【A】When this card becomes REVERSE, if this card's battle opponent's Level is higher than opponent's Level, you may place that Character to Stock. If you did, place the bottom card of opponent's Stock into Waiting Room."
        ],
        "attributes": [
            "Music 《音楽》"
        ],
        "set": "SG",
        "release": "W70",
        "sid": "020",
        "image": "https://images.littleakiba.com/tcg/card53251-large.jpg"
    },
    {
        "name": "出撃！ 響",
        "code": "SG/W70-021",
        "rarity": "C",
        "expansion": "Senki Zesshou Symphogear AXZ",
        "side": "W",
        "type": "Character",
        "color": "YELLOW",
        "level": "2",
        "cost": "2",
        "trigger": [
            "SOUL"
        ],
        "power": "9000",
        "soul": 2,
        "flavor_text": "-",
        "ability": [
            ""
        ],
        "attributes": [
            "Music 《音楽》"
        ],
        "set": "SG",
        "release": "W70",
        "sid": "021",
        "image": "https://images.littleakiba.com/tcg/card53252-large.jpg"
    },
    {
        "name": "イグナイトモジュール",
        "code": "SG/W70-022",
        "rarity": "U",
        "expansion": "Senki Zesshou Symphogear AXZ",
        "side": "W",
        "type": "Event",
        "color": "YELLOW",
        "level": "1",
        "cost": "1",
        "trigger": [],
        "power": "N/A",
        "soul": 0,
        "flavor_text": "-",
        "ability": [
            "If you have no Character with 「響」 or 「切歌」 in its name, you cannot play this card from Hand.",
            "You draw up to 2 cards, choose 1 card from your Hand, place it into Waiting Room. Send this card to Memory."
        ],
        "attributes": [],
        "set": "SG",
        "release": "W70",
        "sid": "022",
        "image": "https://images.littleakiba.com/tcg/card53253-large.jpg"
    },
    {
        "name": "TESTAMENT",
        "code": "SG/W70-023",
        "rarity": "CR",
        "expansion": "Senki Zesshou Symphogear AXZ",
        "side": "W",
        "type": "Climax",
        "color": "YELLOW",
        "level": "0",
        "cost": "0",
        "trigger": [
            "CHOICE"
        ],
        "power": "N/A",
        "soul": 0,
        "flavor_text": "-",
        "ability": [
            "【C】 All your Characters get +1000 Power, +1 Soul.",
            "(Flame：When this card is Triggered, if your current attacking Character's damage is cancelled, deal 1 damage to your opponent)"
        ],
        "attributes": [],
        "set": "SG",
        "release": "W70",
        "sid": "023",
        "image": "https://images.littleakiba.com/tcg/card53254-large.jpg"
    },
    {
        "name": "必愛デュオシャウト",
        "code": "SG/W70-024",
        "rarity": "CC",
        "expansion": "Senki Zesshou Symphogear AXZ",
        "side": "W",
        "type": "Climax",
        "color": "YELLOW",
        "level": "0",
        "cost": "0",
        "trigger": [
            "SOUL",
            "SOUL"
        ],
        "power": "N/A",
        "soul": 0,
        "flavor_text": "-",
        "ability": [
            "【A】 When this card is placed into Climax slot from Hand, choose up to 1 Yellow card from your Waiting Room, place it to Stock, during this turn, all your Characters get +1 Soul."
        ],
        "attributes": [],
        "set": "SG",
        "release": "W70",
        "sid": "024",
        "image": "https://images.littleakiba.com/tcg/card53256-large.jpg"
    },
    {
        "name": "黄金錬成",
        "code": "SG/W70-025",
        "rarity": "CC",
        "expansion": "Senki Zesshou Symphogear AXZ",
        "side": "W",
        "type": "Climax",
        "color": "YELLOW",
        "level": "0",
        "cost": "0",
        "trigger": [
            "SOUL",
            "RETURN"
        ],
        "power": "N/A",
        "soul": 0,
        "flavor_text": "-",
        "ability": [
            "【C】 All your Characters gets +1000 Power, +1 Soul.",
            "(Wind：When this card is Triggered, you may choose 1 of your opponent's Character, return it to Hand)"
        ],
        "attributes": [],
        "set": "SG",
        "release": "W70",
        "sid": "025",
        "image": "https://images.littleakiba.com/tcg/card53257-large.jpg"
    },
    {
        "name": "想いを束ねて 調",
        "code": "SG/W70-026",
        "rarity": "RR",
        "expansion": "Senki Zesshou Symphogear AXZ",
        "side": "W",
        "type": "Character",
        "color": "GREEN",
        "level": "0",
        "cost": "0",
        "trigger": [],
        "power": "1000",
        "soul": 1,
        "flavor_text": "-",
        "ability": [
            "【A】When this card is placed on Stage from Hand, choose up to 2 opponent's Character, during this turn, they get -500 Power.",
            "【A】[(1)] When a Climax is placed into your Climax Slot, you may pay the cost. If you did, look at up to 4 cards from your top Deck, choose up to 1 《音楽》 Character, and show it to opponent, add it to Hand, place the remaining cards into Waiting Room."
        ],
        "attributes": [
            "Music 《音楽》",
            "Weapon 《武器》"
        ],
        "set": "SG",
        "release": "W70",
        "sid": "026",
        "image": "https://images.littleakiba.com/tcg/card53258-large.jpg"
    },
    {
        "name": "二人の時間 調＆切歌",
        "code": "SG/W70-027",
        "rarity": "RR",
        "expansion": "Senki Zesshou Symphogear AXZ",
        "side": "W",
        "type": "Character",
        "color": "GREEN",
        "level": "0",
        "cost": "0",
        "trigger": [],
        "power": "1000",
        "soul": 1,
        "flavor_text": "-",
        "ability": [
            "【A】[(1) Place the top card of your Deck into Clock] When this card is placed on Stage from Hand, you may pay the cost. If you did, search your Deck for up to 1 Character with 「切歌」 or 「調」 in its name and show it to opponent, add it to Hand, shuffle your Deck afterwards.",
            "【A】When this card attacks, choose 1 of your other Character with 「切歌」 or 「調」 in its name, during this turn, it gets +1000 Power."
        ],
        "attributes": [
            "Music 《音楽》",
            "Weapon 《武器》"
        ],
        "set": "SG",
        "release": "W70",
        "sid": "027",
        "image": "https://images.littleakiba.com/tcg/card53260-large.jpg"
    },
    {
        "name": "想いを束ねて 切歌",
        "code": "SG/W70-028",
        "rarity": "RR",
        "expansion": "Senki Zesshou Symphogear AXZ",
        "side": "W",
        "type": "Character",
        "color": "GREEN",
        "level": "1",
        "cost": "0",
        "trigger": [],
        "power": "5000",
        "soul": 1,
        "flavor_text": "-",
        "ability": [
            "【A】【CXCOMBO】When this card attacks, if 「切・呪りeッTぉ」 is in your Climax Slot, and all your Character has 「響」 or 「切歌」 in its name, you may choose 1 Character with 「響」 or 「切歌」 in its name from your Waiting Room, return it to Hand."
        ],
        "attributes": [
            "Music 《音楽》",
            "Weapon 《武器》"
        ],
        "set": "SG",
        "release": "W70",
        "sid": "028",
        "image": "https://images.littleakiba.com/tcg/card53262-large.jpg"
    },
    {
        "name": "終わりなき闘争 切歌",
        "code": "SG/W70-029",
        "rarity": "R",
        "expansion": "Senki Zesshou Symphogear AXZ",
        "side": "W",
        "type": "Character",
        "color": "GREEN",
        "level": "0",
        "cost": "0",
        "trigger": [],
        "power": "2000",
        "soul": 1,
        "flavor_text": "-",
        "ability": [
            "【C】If you have 2 or more other 《音楽》 Character, this card gets +1000 Power.",
            "【A】When this card is placed on Stage from Hand, choose 1 of your other 《音楽》 Character, during this turn, it gets +X Power. X is equal to the number of your other 《音楽》 Character x500."
        ],
        "attributes": [
            "Music 《音楽》",
            "Weapon 《武器》"
        ],
        "set": "SG",
        "release": "W70",
        "sid": "029",
        "image": "https://images.littleakiba.com/tcg/card53264-large.jpg"
    },
    {
        "name": "終わりなき闘争 調",
        "code": "SG/W70-030",
        "rarity": "R",
        "expansion": "Senki Zesshou Symphogear AXZ",
        "side": "W",
        "type": "Character",
        "color": "GREEN",
        "level": "1",
        "cost": "0",
        "trigger": [],
        "power": "4000",
        "soul": 1,
        "flavor_text": "-",
        "ability": [
            "【C】For each of your other 《音楽》 Character, this card gets +500 Power.",
            "【A】RESONANCE [(1) Reveal 1 「新たな戦い 翼」 from Hand] When this card attacks, you may pay the cost. If you did, during this attack, perform Trigger Check 2 times during Trigger Step."
        ],
        "attributes": [
            "Music 《音楽》",
            "Weapon 《武器》"
        ],
        "set": "SG",
        "release": "W70",
        "sid": "030",
        "image": "https://images.littleakiba.com/tcg/card53266-large.jpg"
    },
    {
        "name": "新たな戦い 調",
        "code": "SG/W70-031",
        "rarity": "R",
        "expansion": "Senki Zesshou Symphogear AXZ",
        "side": "W",
        "type": "Character",
        "color": "GREEN",
        "level": "3",
        "cost": "2",
        "trigger": [
            "SOUL"
        ],
        "power": "9000",
        "soul": 2,
        "flavor_text": "-",
        "ability": [
            "【C】If you have 4 or more 《音楽》 Character, this card gets -1 Level in your Hand.",
            "【A】When this card is placed on Stage from Hand, you may place the top card of your Clock into Waiting Room.",
            "【A】When this card attacks, choose 1 of your other 《音楽》 Character, during this turn, it gets +X Power. X is equal to the number of your other 《音楽》 Character x500."
        ],
        "attributes": [
            "Music 《音楽》",
            "Weapon 《武器》"
        ],
        "set": "SG",
        "release": "W70",
        "sid": "031",
        "image": "https://images.littleakiba.com/tcg/card53268-large.jpg"
    },
    {
        "name": "新たな戦い 切歌",
        "code": "SG/W70-032",
        "rarity": "R",
        "expansion": "Senki Zesshou Symphogear AXZ",
        "side": "W",
        "type": "Character",
        "color": "GREEN",
        "level": "3",
        "cost": "2",
        "trigger": [
            "SOUL"
        ],
        "power": "10000",
        "soul": 2,
        "flavor_text": "-",
        "ability": [
            "【A】When this card is placed on Stage from Hand, reveal the top card of your Deck. If that card is a 《音楽》 Character, you may deal 1 Damage to opponent. (Damage can be cancelled. Return revealed card to its original position)",
            "【A】RESONANCE [Reveal 1 「新たな戦い 響」 from Hand] When this card is placed on Stage from Hand, you may pay the cost. If you did, choose 1 of your Character with 「響」 or 「切歌」 in its name, during this turn, it gets +3000 Power, gains the following Ability. 『【C】This card cannot be chosen by opponent's effect.』"
        ],
        "attributes": [
            "Music 《音楽》",
            "Weapon 《武器》"
        ],
        "set": "SG",
        "release": "W70",
        "sid": "032",
        "image": "https://images.littleakiba.com/tcg/card53270-large.jpg"
    },
    {
        "name": "異様な光景 調",
        "code": "SG/W70-033",
        "rarity": "U",
        "expansion": "Senki Zesshou Symphogear AXZ",
        "side": "W",
        "type": "Character",
        "color": "GREEN",
        "level": "0",
        "cost": "0",
        "trigger": [],
        "power": "1000",
        "soul": 1,
        "flavor_text": "-",
        "ability": [
            "【C】SUPPORT All your Character in front of this card gets +500 Power.",
            "【S】[(2) REST this card] Search your Deck for up to 1 《音楽》 Character and show it to opponent, add it to Hand, shuffle your Deck afterwards."
        ],
        "attributes": [
            "Music 《音楽》",
            "Weapon 《武器》"
        ],
        "set": "SG",
        "release": "W70",
        "sid": "033",
        "image": "https://images.littleakiba.com/tcg/card53272-large.jpg"
    },
    {
        "name": "無償の想い 調",
        "code": "SG/W70-034",
        "rarity": "U",
        "expansion": "Senki Zesshou Symphogear AXZ",
        "side": "W",
        "type": "Character",
        "color": "GREEN",
        "level": "0",
        "cost": "0",
        "trigger": [],
        "power": "2000",
        "soul": 1,
        "flavor_text": "-",
        "ability": [
            "【C】If you have 2 or more other 《音楽》 Character, this card gets +1000 Power.",
            "【A】[(1) Place 1 card from Hand into Waiting Room] When this card is placed on Stage from Hand, you may pay the cost. If you did, search your Deck for up to 1 《音楽》 Character, and show it to opponent, add it to Hand, shuffle your Deck afterwards."
        ],
        "attributes": [
            "Music 《音楽》",
            "Weapon 《武器》"
        ],
        "set": "SG",
        "release": "W70",
        "sid": "034",
        "image": "https://images.littleakiba.com/tcg/card53273-large.jpg"
    },
    {
        "name": "不退転の覚悟 切歌",
        "code": "SG/W70-035",
        "rarity": "U",
        "expansion": "Senki Zesshou Symphogear AXZ",
        "side": "W",
        "type": "Character",
        "color": "GREEN",
        "level": "0",
        "cost": "0",
        "trigger": [],
        "power": "2500",
        "soul": 1,
        "flavor_text": "-",
        "ability": [
            "【A】[Place the top card of your Deck into Clock] When this card is placed into Waiting Room from Stage, you may pay the cost. If you did, reveal the top card of your Deck. If that card is a 《音楽》 Character, add it to Hand. (If not, return revealed card to its original position)"
        ],
        "attributes": [
            "Music 《音楽》",
            "Weapon 《武器》"
        ],
        "set": "SG",
        "release": "W70",
        "sid": "035",
        "image": "https://images.littleakiba.com/tcg/card53274-large.jpg"
    },
    {
        "name": "不退転の覚悟 調",
        "code": "SG/W70-036",
        "rarity": "U",
        "expansion": "Senki Zesshou Symphogear AXZ",
        "side": "W",
        "type": "Character",
        "color": "GREEN",
        "level": "1",
        "cost": "0",
        "trigger": [],
        "power": "4500",
        "soul": 1,
        "flavor_text": "-",
        "ability": [
            "【A】【CXCOMBO】When this card attacks, if 「α式百輪廻」 is in your Climax Slot, and you have 2 or more other 《音楽》 Character, reveal 2 cards from your top Deck, opponent choose 1 Character or Event among those cards, add it to your Hand, place the remaining cards into Waiting Room.",
            "【A】When this card attacks, if you have 2 or more other 《音楽》 Character, during this turn, this card gets +2000 Power."
        ],
        "attributes": [
            "Music 《音楽》",
            "Weapon 《武器》"
        ],
        "set": "SG",
        "release": "W70",
        "sid": "036",
        "image": "https://images.littleakiba.com/tcg/card53275-large.jpg"
    },
    {
        "name": "力の使い方 調",
        "code": "SG/W70-037",
        "rarity": "U",
        "expansion": "Senki Zesshou Symphogear AXZ",
        "side": "W",
        "type": "Character",
        "color": "GREEN",
        "level": "2",
        "cost": "1",
        "trigger": [
            "SOUL"
        ],
        "power": "2500",
        "soul": 1,
        "flavor_text": "-",
        "ability": [
            "【A】 ［Place 2 cards into Waiting Room from Hand］ When you use this card's 『ASSIST』, you may pay the cost. If you did, choose 1 of your opponent's Character with Level higher than your opponent, place it into Waiting Room.",
            "【S】【COUNTER】 ASSIST 2500 Level 2 ［(1) Place this card from Hand into Waiting Room］ (Choose 1 of your Characters being Front Attacked, during that turn, it gets +2500 Power)"
        ],
        "attributes": [
            "Music 《音楽》",
            "Weapon 《武器》"
        ],
        "set": "SG",
        "release": "W70",
        "sid": "037",
        "image": "https://images.littleakiba.com/tcg/card53276-large.jpg"
    },
    {
        "name": "絆のユニゾン 切歌",
        "code": "SG/W70-038",
        "rarity": "U",
        "expansion": "Senki Zesshou Symphogear AXZ",
        "side": "W",
        "type": "Character",
        "color": "GREEN",
        "level": "2",
        "cost": "1",
        "trigger": [
            "SOUL"
        ],
        "power": "6500",
        "soul": 1,
        "flavor_text": "-",
        "ability": [
            "【A】【CXCOMBO】When 「必愛デュオシャウト」 is placed into your Climax Slot, if this card is at Front Row, search your Deck for up to 1 《音楽》 Character and show it to opponent, add it to Hand, shuffle your Deck afterwards.",
            "【A】When this card becomes REVERSE, if this card's battle opponent's Level is higher than opponent's Level, you may place the top card of opponent's Clock into Waiting Room. If you did, place that Character into Clock."
        ],
        "attributes": [
            "Music 《音楽》",
            "Weapon 《武器》"
        ],
        "set": "SG",
        "release": "W70",
        "sid": "038",
        "image": "https://images.littleakiba.com/tcg/card53277-large.jpg"
    },
    {
        "name": "見回り中 調",
        "code": "SG/W70-039",
        "rarity": "C",
        "expansion": "Senki Zesshou Symphogear AXZ",
        "side": "W",
        "type": "Character",
        "color": "GREEN",
        "level": "0",
        "cost": "0",
        "trigger": [],
        "power": "500",
        "soul": 1,
        "flavor_text": "-",
        "ability": [
            "【C】During your turn, all your other 「見回り中 切歌」 gets +2000 Power.",
            "【A】BOND／「見回り中 切歌」 ［Place the top card of your Deck into Clock］(When this card is played onto Stage, you may pay the cost. If you did, choose 1 「見回り中 切歌」 from your Waiting Room, return it to Hand)"
        ],
        "attributes": [
            "Music 《音楽》",
            "Weapon 《武器》"
        ],
        "set": "SG",
        "release": "W70",
        "sid": "039",
        "image": "https://images.littleakiba.com/tcg/card53278-large.jpg"
    },
    {
        "name": "受け継がれる伝承 切歌",
        "code": "SG/W70-040",
        "rarity": "C",
        "expansion": "Senki Zesshou Symphogear AXZ",
        "side": "W",
        "type": "Character",
        "color": "GREEN",
        "level": "0",
        "cost": "0",
        "trigger": [],
        "power": "2000",
        "soul": 1,
        "flavor_text": "-",
        "ability": [
            "【A】 When your other 《音楽》 Character attacks, during this turn, this card gets ＋1500 Power."
        ],
        "attributes": [
            "Music 《音楽》",
            "Weapon 《武器》"
        ],
        "set": "SG",
        "release": "W70",
        "sid": "040",
        "image": "https://images.littleakiba.com/tcg/card53279-large.jpg"
    },
    {
        "name": "絆のユニゾン 調",
        "code": "SG/W70-041",
        "rarity": "C",
        "expansion": "Senki Zesshou Symphogear AXZ",
        "side": "W",
        "type": "Character",
        "color": "GREEN",
        "level": "0",
        "cost": "0",
        "trigger": [],
        "power": "2500",
        "soul": 1,
        "flavor_text": "-",
        "ability": [
            "【A】【CXCOMBO】When this card attacks, if 「風月ノ疾双」 is in your Climax Slot, if you have other 《音楽》 Character, during this turn, this card gets +1500 Power, gains the following Ability. 『【A】At the end of battle when this card attacks, you may place this card into Stock.』"
        ],
        "attributes": [
            "Music 《音楽》",
            "Weapon 《武器》"
        ],
        "set": "SG",
        "release": "W70",
        "sid": "041",
        "image": "https://images.littleakiba.com/tcg/card53280-large.jpg"
    },
    {
        "name": "見回り中 切歌",
        "code": "SG/W70-042",
        "rarity": "C",
        "expansion": "Senki Zesshou Symphogear AXZ",
        "side": "W",
        "type": "Character",
        "color": "GREEN",
        "level": "0",
        "cost": "0",
        "trigger": [],
        "power": "5500",
        "soul": 1,
        "flavor_text": "-",
        "ability": [
            ""
        ],
        "attributes": [
            "Music 《音楽》",
            "Weapon 《武器》"
        ],
        "set": "SG",
        "release": "W70",
        "sid": "042",
        "image": "https://images.littleakiba.com/tcg/card53281-large.jpg"
    },
    {
        "name": "突然の強襲 アルカ・ノイズ",
        "code": "SG/W70-043",
        "rarity": "C",
        "expansion": "Senki Zesshou Symphogear AXZ",
        "side": "W",
        "type": "Character",
        "color": "GREEN",
        "level": "2",
        "cost": "1",
        "trigger": [],
        "power": "6500",
        "soul": 1,
        "flavor_text": "-",
        "ability": [
            "【A】［(1)］ When this card is placed on Stage from Hand, if you have other 《錬金術》 or 《ノイズ》 Character, you may pay the cost. If you did, choose up to 2 《錬金術》 or 《ノイズ》 Character with Level 0 or lower from your Waiting Room, place them into separate slot on Stage.",
            "【A】 When this card attacks, if the Character facing this card is Level 3 or higher, during this turn, this card gets ＋6000 Power."
        ],
        "attributes": [
            "Alchemy 《錬金術》",
            "Noise 《ノイズ》"
        ],
        "set": "SG",
        "release": "W70",
        "sid": "043",
        "image": "https://images.littleakiba.com/tcg/card53282-large.jpg"
    },
    {
        "name": "イグナイトモジュール",
        "code": "SG/W70-044",
        "rarity": "U",
        "expansion": "Senki Zesshou Symphogear AXZ",
        "side": "W",
        "type": "Event",
        "color": "GREEN",
        "level": "3",
        "cost": "2",
        "trigger": [],
        "power": "N/A",
        "soul": 0,
        "flavor_text": "-",
        "ability": [
            "If you have no Character with 「翼」 or 「調」 in its name, you cannot play this card from Hand.",
            "Place 4 cards from your top Deck into Waiting Room, deal X Damage to opponent. X is equal to the number of cards that has Soul Trigger Icon or 「イグナイトモジュール」 among those cards. (Damage can be cancelled)",
            "Choose 1 of your Character, during this turn, it gets +1000 Power. Send this card to Memory."
        ],
        "attributes": [],
        "set": "SG",
        "release": "W70",
        "sid": "044",
        "image": "https://images.littleakiba.com/tcg/card53283-large.jpg"
    },
    {
        "name": "切・呪りeッTぉ",
        "code": "SG/W70-045",
        "rarity": "CR",
        "expansion": "Senki Zesshou Symphogear AXZ",
        "side": "W",
        "type": "Climax",
        "color": "GREEN",
        "level": "0",
        "cost": "0",
        "trigger": [
            "TREASURE"
        ],
        "power": "N/A",
        "soul": 0,
        "flavor_text": "-",
        "ability": [
            "【C】 All your Characters get +1000 Power, +1 Soul.",
            "(Gold：When this card is Triggered, return this card to your Hand. You may place the top card of your Deck into Stock)"
        ],
        "attributes": [],
        "set": "SG",
        "release": "W70",
        "sid": "045",
        "image": "https://images.littleakiba.com/tcg/card53284-large.jpg"
    },
    {
        "name": "α式百輪廻",
        "code": "SG/W70-046",
        "rarity": "CC",
        "expansion": "Senki Zesshou Symphogear AXZ",
        "side": "W",
        "type": "Climax",
        "color": "GREEN",
        "level": "0",
        "cost": "0",
        "trigger": [
            "TREASURE"
        ],
        "power": "N/A",
        "soul": 0,
        "flavor_text": "-",
        "ability": [
            "【C】 All your Characters get +1000 Power, +1 Soul.",
            "(Gold：When this card is Triggered, return this card to your Hand. You may place the top card of your Deck into Stock)"
        ],
        "attributes": [],
        "set": "SG",
        "release": "W70",
        "sid": "046",
        "image": "https://images.littleakiba.com/tcg/card53286-large.jpg"
    },
    {
        "name": "風月ノ疾双",
        "code": "SG/W70-047",
        "rarity": "CC",
        "expansion": "Senki Zesshou Symphogear AXZ",
        "side": "W",
        "type": "Climax",
        "color": "GREEN",
        "level": "0",
        "cost": "0",
        "trigger": [
            "SOUL",
            "SOUL"
        ],
        "power": "N/A",
        "soul": 0,
        "flavor_text": "-",
        "ability": [
            "【A】 When this card is placed into Climax slot from Hand, choose up to 1 Green card from your Waiting Room, place it to Stock, during this turn, all your Characters get +1 Soul."
        ],
        "attributes": [],
        "set": "SG",
        "release": "W70",
        "sid": "047",
        "image": "https://images.littleakiba.com/tcg/card53288-large.jpg"
    },
    {
        "name": "想いを束ねて クリス",
        "code": "SG/W70-048",
        "rarity": "RR",
        "expansion": "Senki Zesshou Symphogear AXZ",
        "side": "W",
        "type": "Character",
        "color": "RED",
        "level": "0",
        "cost": "0",
        "trigger": [],
        "power": "2000",
        "soul": 1,
        "flavor_text": "-",
        "ability": [
            "【A】When this card attacks, choose 1 of your Character, during this turn, it gets +500 Power.",
            "【A】At the beginning of opponent's Attack Phase, you may place the top card of your Deck into Waiting Room. If that card is a 《音楽》 Character, you may move this card to an empty slot at Front Row."
        ],
        "attributes": [
            "Music 《音楽》",
            "Weapon 《武器》"
        ],
        "set": "SG",
        "release": "W70",
        "sid": "048",
        "image": "https://images.littleakiba.com/tcg/card53289-large.jpg"
    },
    {
        "name": "想いを束ねて マリア",
        "code": "SG/W70-049",
        "rarity": "RR",
        "expansion": "Senki Zesshou Symphogear AXZ",
        "side": "W",
        "type": "Character",
        "color": "RED",
        "level": "3",
        "cost": "2",
        "trigger": [
            "SOUL"
        ],
        "power": "7500",
        "soul": 2,
        "flavor_text": "-",
        "ability": [
            "【C】SUPPORT All your 《音楽》 Character in front of this card gets +2000 Power.",
            "【A】[Place 1 card from Hand into Waiting Room] When this card is placed on Stage from Hand, you may pay the cost. If you did, place the top card of your Clock into Stock.",
            "【A】RESONANCE [Reveal 1 「繋ぐ力 クリス」 from Hand] At the beginning of your Climax Phase, you may pay the cost. If you did, look at up to 2 cards from your top Deck, place them on top Deck in any order."
        ],
        "attributes": [
            "Music 《音楽》",
            "Weapon 《武器》"
        ],
        "set": "SG",
        "release": "W70",
        "sid": "049",
        "image": "https://images.littleakiba.com/tcg/card53291-large.jpg"
    },
    {
        "name": "新たな戦い クリス",
        "code": "SG/W70-050",
        "rarity": "RR",
        "expansion": "Senki Zesshou Symphogear AXZ",
        "side": "W",
        "type": "Character",
        "color": "RED",
        "level": "3",
        "cost": "2",
        "trigger": [
            "SOUL"
        ],
        "power": "9000",
        "soul": 2,
        "flavor_text": "-",
        "ability": [
            "【C】EXPERIENCE If 「新たな戦い クリス」 is in your Climax Slot, this card gets +2000 Power.",
            "【A】When this card is placed on Stage from Hand, draw up to 2 cards, choose 1 card from your Hand, place it into Waiting Room.",
            "【A】【CXCOMBO】[(2) Place 1 card from Hand into Waiting Room] When this card attacks, if 「QUEEN's INFERNO」 is in your Climax Slot, you may pay the cost. If you did, deal 3 Damage to opponent, during this turn, this card gets +1000 Power."
        ],
        "attributes": [
            "Music 《音楽》",
            "Weapon 《武器》"
        ],
        "set": "SG",
        "release": "W70",
        "sid": "050",
        "image": "https://images.littleakiba.com/tcg/card53293-large.jpg"
    },
    {
        "name": "狙い撃ち クリス",
        "code": "SG/W70-051",
        "rarity": "R",
        "expansion": "Senki Zesshou Symphogear AXZ",
        "side": "W",
        "type": "Character",
        "color": "RED",
        "level": "0",
        "cost": "0",
        "trigger": [],
        "power": "500",
        "soul": 1,
        "flavor_text": "-",
        "ability": [
            "【C】SUPPORT All your Character in front of this card gets +500 Power.",
            "【S】CONCENTRATION ［(1)］ Flip the top 4 cards of your Deck, place them into Waiting Room. For each Climax among those cards, perform the following Action.『Choose 1 Character from your Waiting Room, return it to Hand, choose 1 card from your Hand, place it into Waiting Room.』"
        ],
        "attributes": [
            "Music 《音楽》",
            "Weapon 《武器》"
        ],
        "set": "SG",
        "release": "W70",
        "sid": "051",
        "image": "https://images.littleakiba.com/tcg/card53295-large.jpg"
    },
    {
        "name": "二人の時間 マリア＆翼",
        "code": "SG/W70-052",
        "rarity": "R",
        "expansion": "Senki Zesshou Symphogear AXZ",
        "side": "W",
        "type": "Character",
        "color": "RED",
        "level": "0",
        "cost": "0",
        "trigger": [],
        "power": "2500",
        "soul": 1,
        "flavor_text": "-",
        "ability": [
            "【A】[(1) Place the top card of your Deck into Clock, place 2 cards from Hand into Waiting Room] When this card is placed on Stage from Hand, you may pay the cost. If you did, search your Deck for up to 1 Character with 「翼」 in its name and up to 1 Character with 「マリア」 in its name and show them to opponent, add them to Hand, shuffle your Deck afterwards, during this turn, this card gets +3000 Power."
        ],
        "attributes": [
            "Music 《音楽》",
            "Weapon 《武器》"
        ],
        "set": "SG",
        "release": "W70",
        "sid": "052",
        "image": "https://images.littleakiba.com/tcg/card53297-large.jpg"
    },
    {
        "name": "スイカ割り マリア",
        "code": "SG/W70-053",
        "rarity": "R",
        "expansion": "Senki Zesshou Symphogear AXZ",
        "side": "W",
        "type": "Character",
        "color": "RED",
        "level": "1",
        "cost": "0",
        "trigger": [],
        "power": "4000",
        "soul": 1,
        "flavor_text": "-",
        "ability": [
            "【C】During your turn, all your other Character with 「クリス」 or 「マリア」 in its name gets +1000 Power.",
            "【S】[(2) REST this card] Choose 1 Character with 「クリス」 or 「マリア」 in its name from your Waiting Room, return it to Hand."
        ],
        "attributes": [
            "Music 《音楽》",
            "Weapon 《武器》"
        ],
        "set": "SG",
        "release": "W70",
        "sid": "053",
        "image": "https://images.littleakiba.com/tcg/card53299-large.jpg"
    },
    {
        "name": "新たな戦い マリア",
        "code": "SG/W70-054",
        "rarity": "R",
        "expansion": "Senki Zesshou Symphogear AXZ",
        "side": "W",
        "type": "Character",
        "color": "RED",
        "level": "1",
        "cost": "0",
        "trigger": [],
        "power": "4500",
        "soul": 1,
        "flavor_text": "-",
        "ability": [
            "【C】During your turn, if you have other 《音楽》 Character, this card gets +1500 Power.",
            "【A】【CXCOMBO】When this card's battle opponent becomes REVERSE, if 「HORIZON†CANNON」 is in your Climax Slot, you may choose 1 Character from your Waiting Room, return it to Hand."
        ],
        "attributes": [
            "Music 《音楽》",
            "Weapon 《武器》"
        ],
        "set": "SG",
        "release": "W70",
        "sid": "054",
        "image": "https://images.littleakiba.com/tcg/card53301-large.jpg"
    },
    {
        "name": "繋ぐ力 クリス",
        "code": "SG/W70-055",
        "rarity": "R",
        "expansion": "Senki Zesshou Symphogear AXZ",
        "side": "W",
        "type": "Character",
        "color": "RED",
        "level": "1",
        "cost": "0",
        "trigger": [],
        "power": "5000",
        "soul": 1,
        "flavor_text": "-",
        "ability": [
            "【A】RESONANCE [Reveal 1 「想いを束ねて マリア」 from Hand] When this card is placed on Stage from Hand, you may pay the cost. If you did, during this turn, this card gets +1000 Power, gains the following Ability. 『【A】When this card's battle opponent becomes REVERSE, you may place that Character to top Deck.』"
        ],
        "attributes": [
            "Music 《音楽》",
            "Weapon 《武器》"
        ],
        "set": "SG",
        "release": "W70",
        "sid": "055",
        "image": "https://images.littleakiba.com/tcg/card53303-large.jpg"
    },
    {
        "name": "終わりなき闘争 クリス",
        "code": "SG/W70-056",
        "rarity": "U",
        "expansion": "Senki Zesshou Symphogear AXZ",
        "side": "W",
        "type": "Character",
        "color": "RED",
        "level": "0",
        "cost": "0",
        "trigger": [],
        "power": "1000",
        "soul": 1,
        "flavor_text": "-",
        "ability": [
            "【A】[(1) Place 1 card from Hand into Waiting Room] When this card is placed on Stage from Hand, you may pay the cost. If you did, look at up to 3 cards from your top Deck, choose up to 1 card, add it to Hand, place the remaining cards into Waiting Room."
        ],
        "attributes": [
            "Music 《音楽》",
            "Weapon 《武器》"
        ],
        "set": "SG",
        "release": "W70",
        "sid": "056",
        "image": "https://images.littleakiba.com/tcg/card53305-large.jpg"
    },
    {
        "name": "ぶっつけ本番 クリス",
        "code": "SG/W70-057",
        "rarity": "U",
        "expansion": "Senki Zesshou Symphogear AXZ",
        "side": "W",
        "type": "Character",
        "color": "RED",
        "level": "0",
        "cost": "0",
        "trigger": [],
        "power": "2000",
        "soul": 1,
        "flavor_text": "-",
        "ability": [
            "【A】[Place 1 《音楽》 Character from Hand into Waiting Room] When this card is placed on Stage from Hand, you may pay the cost. If you did, choose 1 「繋ぐ力 クリス」 or 「想いを束ねて マリア」 from your Waiting Room, return it to Hand.",
            "【S】[Place 1 card from Hand into Waiting Room, place this card into Waiting Room] Choose 1 Character with 「クリス」 or 「マリア」 in its name from your Waiting Room, return it to Hand."
        ],
        "attributes": [
            "Music 《音楽》",
            "Weapon 《武器》"
        ],
        "set": "SG",
        "release": "W70",
        "sid": "057",
        "image": "https://images.littleakiba.com/tcg/card53307-large.jpg"
    },
    {
        "name": "終わりなき闘争 マリア",
        "code": "SG/W70-058",
        "rarity": "U",
        "expansion": "Senki Zesshou Symphogear AXZ",
        "side": "W",
        "type": "Character",
        "color": "RED",
        "level": "0",
        "cost": "0",
        "trigger": [],
        "power": "2000",
        "soul": 1,
        "flavor_text": "-",
        "ability": [
            "【C】The Character facing this card cannot move to other slot.",
            "【A】When this card is placed on Stage from Hand, during this turn, this card gets +1500 Power."
        ],
        "attributes": [
            "Music 《音楽》",
            "Weapon 《武器》"
        ],
        "set": "SG",
        "release": "W70",
        "sid": "058",
        "image": "https://images.littleakiba.com/tcg/card53308-large.jpg"
    },
    {
        "name": "絆のユニゾン マリア",
        "code": "SG/W70-059",
        "rarity": "U",
        "expansion": "Senki Zesshou Symphogear AXZ",
        "side": "W",
        "type": "Character",
        "color": "RED",
        "level": "0",
        "cost": "0",
        "trigger": [],
        "power": "2000",
        "soul": 1,
        "flavor_text": "-",
        "ability": [
            "【A】When this card is placed on Stage from Hand, during this turn, this card gets +1500 Power.",
            "【A】【CXCOMBO】When this card's battle opponent becomes REVERSE, if 「Change the Future」 is in your Climax Slot, choose up to 1 《音楽》 Character from your Waiting Room, return it to Hand, choose 1 of your other Character, during this turn, it gets +1 Level."
        ],
        "attributes": [
            "Music 《音楽》",
            "Weapon 《武器》"
        ],
        "set": "SG",
        "release": "W70",
        "sid": "059",
        "image": "https://images.littleakiba.com/tcg/card53310-large.jpg"
    },
    {
        "name": "踏み込むべき一歩 クリス",
        "code": "SG/W70-060",
        "rarity": "U",
        "expansion": "Senki Zesshou Symphogear AXZ",
        "side": "W",
        "type": "Character",
        "color": "RED",
        "level": "1",
        "cost": "0",
        "trigger": [],
        "power": "4500",
        "soul": 1,
        "flavor_text": "-",
        "ability": [
            "【C】For each of your other 《音楽》 Character, this card gets +500 Power."
        ],
        "attributes": [
            "Music 《音楽》",
            "Weapon 《武器》"
        ],
        "set": "SG",
        "release": "W70",
        "sid": "060",
        "image": "https://images.littleakiba.com/tcg/card53311-large.jpg"
    },
    {
        "name": "絆のユニゾン クリス",
        "code": "SG/W70-061",
        "rarity": "U",
        "expansion": "Senki Zesshou Symphogear AXZ",
        "side": "W",
        "type": "Character",
        "color": "RED",
        "level": "2",
        "cost": "1",
        "trigger": [],
        "power": "6000",
        "soul": 1,
        "flavor_text": "-",
        "ability": [
            "【C】For each of your other 《音楽》 Character, this card gets +1000 Power.",
            "【A】【CXCOMBO】[(1)] When this card attacks, if 「Change the Future」 is in your Climax Slot, you may pay the cost. If you did, choose 1 opponent's Character with Level 1 or lower, place it into Waiting Room."
        ],
        "attributes": [
            "Music 《音楽》",
            "Weapon 《武器》"
        ],
        "set": "SG",
        "release": "W70",
        "sid": "061",
        "image": "https://images.littleakiba.com/tcg/card53312-large.jpg"
    },
    {
        "name": "不退転の覚悟 マリア",
        "code": "SG/W70-062",
        "rarity": "U",
        "expansion": "Senki Zesshou Symphogear AXZ",
        "side": "W",
        "type": "Character",
        "color": "RED",
        "level": "2",
        "cost": "1",
        "trigger": [],
        "power": "7500",
        "soul": 1,
        "flavor_text": "-",
        "ability": [
            "【A】When this card attacks, if the Character facing this card is Level 3 or higher, during this turn, this card gets +6000 Power."
        ],
        "attributes": [
            "Music 《音楽》",
            "Weapon 《武器》"
        ],
        "set": "SG",
        "release": "W70",
        "sid": "062",
        "image": "https://images.littleakiba.com/tcg/card53313-large.jpg"
    },
    {
        "name": "厳しさを耐えた先に マリア",
        "code": "SG/W70-063",
        "rarity": "C",
        "expansion": "Senki Zesshou Symphogear AXZ",
        "side": "W",
        "type": "Character",
        "color": "RED",
        "level": "0",
        "cost": "0",
        "trigger": [],
        "power": "1500",
        "soul": 1,
        "flavor_text": "-",
        "ability": [
            "【C】 All your other 《音楽》 Character gets ＋500 Power.",
            "【A】 When your Character Trigger Checks a Climax, if that Trigger Icon is Gate, choose 1 of your Character, until end of opponent's next turn, it gets ＋1000 Power."
        ],
        "attributes": [
            "Music 《音楽》",
            "Weapon 《武器》"
        ],
        "set": "SG",
        "release": "W70",
        "sid": "063",
        "image": "https://images.littleakiba.com/tcg/card53314-large.jpg"
    },
    {
        "name": "バースディ・パーティ マリア",
        "code": "SG/W70-064",
        "rarity": "C",
        "expansion": "Senki Zesshou Symphogear AXZ",
        "side": "W",
        "type": "Character",
        "color": "RED",
        "level": "0",
        "cost": "0",
        "trigger": [],
        "power": "3000",
        "soul": 1,
        "flavor_text": "-",
        "ability": [
            ""
        ],
        "attributes": [
            "Music 《音楽》",
            "Weapon 《武器》"
        ],
        "set": "SG",
        "release": "W70",
        "sid": "064",
        "image": "https://images.littleakiba.com/tcg/card53315-large.jpg"
    },
    {
        "name": "抜剣封殺 マリア",
        "code": "SG/W70-065",
        "rarity": "C",
        "expansion": "Senki Zesshou Symphogear AXZ",
        "side": "W",
        "type": "Character",
        "color": "RED",
        "level": "1",
        "cost": "0",
        "trigger": [],
        "power": "1500",
        "soul": 1,
        "flavor_text": "-",
        "ability": [
            "【C】If you have 2 or more other 《音楽》 Character, this card gets +2000 Power.",
            "【A】When this card is placed on Stage from Hand, reveal the top card of your Deck. If that card is a 《音楽》 Character, choose up to 2 opponent's Character with Cost 0 or lower. Those Character cannot STAND during opponent's next Standby Phase. (Return revealed card to its original position)"
        ],
        "attributes": [
            "Music 《音楽》",
            "Weapon 《武器》"
        ],
        "set": "SG",
        "release": "W70",
        "sid": "065",
        "image": "https://images.littleakiba.com/tcg/card53316-large.jpg"
    },
    {
        "name": "隠しきれない気持ち クリス",
        "code": "SG/W70-066",
        "rarity": "C",
        "expansion": "Senki Zesshou Symphogear AXZ",
        "side": "W",
        "type": "Character",
        "color": "RED",
        "level": "1",
        "cost": "0",
        "trigger": [],
        "power": "5000",
        "soul": 1,
        "flavor_text": "-",
        "ability": [
            "【A】When this card is placed on Stage from Hand, if you have other 《音楽》 Character, during this turn, this card gets +2000 Power."
        ],
        "attributes": [
            "Music 《音楽》",
            "Weapon 《武器》"
        ],
        "set": "SG",
        "release": "W70",
        "sid": "066",
        "image": "https://images.littleakiba.com/tcg/card53317-large.jpg"
    },
    {
        "name": "イグナイトモジュール",
        "code": "SG/W70-067",
        "rarity": "U",
        "expansion": "Senki Zesshou Symphogear AXZ",
        "side": "W",
        "type": "Event",
        "color": "RED",
        "level": "3",
        "cost": "1",
        "trigger": [],
        "power": "N/A",
        "soul": 0,
        "flavor_text": "-",
        "ability": [
            "【COUNTER】If you have no Character with 「クリス」 or 「マリア」 in its name, you cannot play this card from Hand.",
            "You may place the top card of your Clock into Waiting Room.",
            "Choose 1 of your Character, during this turn, it gets +3000 Power. Send this card to Memory."
        ],
        "attributes": [],
        "set": "SG",
        "release": "W70",
        "sid": "067",
        "image": "https://images.littleakiba.com/tcg/card53318-large.jpg"
    },
    {
        "name": "QUEEN's INFERNO",
        "code": "SG/W70-068",
        "rarity": "CR",
        "expansion": "Senki Zesshou Symphogear AXZ",
        "side": "W",
        "type": "Climax",
        "color": "RED",
        "level": "0",
        "cost": "0",
        "trigger": [
            "COMEBACK"
        ],
        "power": "N/A",
        "soul": 0,
        "flavor_text": "-",
        "ability": [
            "【C】 All your Characters get +1000 Power, +1 Soul.",
            "(Gate：When this card is Triggered, you may choose 1 Character from your Waiting Room, return it to Hand)"
        ],
        "attributes": [],
        "set": "SG",
        "release": "W70",
        "sid": "068",
        "image": "https://images.littleakiba.com/tcg/card53319-large.jpg"
    },
    {
        "name": "HORIZON†CANNON",
        "code": "SG/W70-069",
        "rarity": "CC",
        "expansion": "Senki Zesshou Symphogear AXZ",
        "side": "W",
        "type": "Climax",
        "color": "RED",
        "level": "0",
        "cost": "0",
        "trigger": [
            "COMEBACK"
        ],
        "power": "N/A",
        "soul": 0,
        "flavor_text": "-",
        "ability": [
            "【C】 All your Characters get +1000 Power, +1 Soul.",
            "(Gate：When this card is Triggered, you may choose 1 Character from your Waiting Room, return it to Hand)"
        ],
        "attributes": [],
        "set": "SG",
        "release": "W70",
        "sid": "069",
        "image": "https://images.littleakiba.com/tcg/card53321-large.jpg"
    },
    {
        "name": "Change the Future",
        "code": "SG/W70-070",
        "rarity": "CC",
        "expansion": "Senki Zesshou Symphogear AXZ",
        "side": "W",
        "type": "Climax",
        "color": "RED",
        "level": "0",
        "cost": "0",
        "trigger": [
            "SOUL",
            "SOUL"
        ],
        "power": "N/A",
        "soul": 0,
        "flavor_text": "-",
        "ability": [
            "【A】 When this card is placed into Climax slot from Hand, choose up to 1 Red card from your Waiting Room, place it to Stock, during this turn, all your Characters get +1 Soul."
        ],
        "attributes": [],
        "set": "SG",
        "release": "W70",
        "sid": "070",
        "image": "https://images.littleakiba.com/tcg/card53323-large.jpg"
    },
    {
        "name": "想いを束ねて 翼",
        "code": "SG/W70-071",
        "rarity": "RR",
        "expansion": "Senki Zesshou Symphogear AXZ",
        "side": "W",
        "type": "Character",
        "color": "BLUE",
        "level": "0",
        "cost": "0",
        "trigger": [],
        "power": "1500",
        "soul": 1,
        "flavor_text": "-",
        "ability": [
            "【A】At the beginning of your Climax Phase, you may look at the top card of your Deck. (Return it to its original position)",
            "【S】CONCENTRATION ［(1) REST this card］ Flip the top 4 cards of your Deck, place them into Waiting Room. For each Climax among those cards, search your Deck for up to 1 《音楽》 Character and show it to opponent, add it to Hand, shuffle your Deck afterwards."
        ],
        "attributes": [
            "Music 《音楽》",
            "Weapon 《武器》"
        ],
        "set": "SG",
        "release": "W70",
        "sid": "071",
        "image": "https://images.littleakiba.com/tcg/card53324-large.jpg"
    },
    {
        "name": "新たな戦い 翼",
        "code": "SG/W70-072",
        "rarity": "RR",
        "expansion": "Senki Zesshou Symphogear AXZ",
        "side": "W",
        "type": "Character",
        "color": "BLUE",
        "level": "3",
        "cost": "2",
        "trigger": [
            "SOUL"
        ],
        "power": "10000",
        "soul": 2,
        "flavor_text": "-",
        "ability": [
            "【A】【CXCOMBO】When this card attacks, if 「逆羅殺」 is in your Climax Slot, look at up to 2 cards from opponent's top Deck, choose up to 2 cards, place them into Waiting Room, place the remaining cards on top Deck in any order, look at up to 2 cards from your top Deck, choose up to 2 cards, place them into Waiting Room, place the remaining cards on top Deck in any order.",
            "【A】RESONANCE [(2) Reveal 1 「終わりなき闘争 調」When this card is being attacked, you may pay the cost. If you did, choose the Character facing this card, during this turn, it gets -2 Soul, this card gets +2000 Power."
        ],
        "attributes": [
            "Music 《音楽》",
            "Weapon 《武器》"
        ],
        "set": "SG",
        "release": "W70",
        "sid": "072",
        "image": "https://images.littleakiba.com/tcg/card53326-large.jpg"
    },
    {
        "name": "シンフォギア装者との対峙 カリオストロ",
        "code": "SG/W70-073",
        "rarity": "R",
        "expansion": "Senki Zesshou Symphogear AXZ",
        "side": "W",
        "type": "Character",
        "color": "BLUE",
        "level": "0",
        "cost": "0",
        "trigger": [],
        "power": "1000",
        "soul": 1,
        "flavor_text": "-",
        "ability": [
            "【C】All your other 《錬金術》 Character gets +500 Power.",
            "【A】When this card is placed on Stage from Hand, if your Memory has 2 or less cards, you may choose 1 「シンフォギア装者との対峙 カリオストロ」 from your Waiting Room, send it to Memory."
        ],
        "attributes": [
            "Alchemy 《錬金術》"
        ],
        "set": "SG",
        "release": "W70",
        "sid": "073",
        "image": "https://images.littleakiba.com/tcg/card53328-large.jpg"
    },
    {
        "name": "シンフォギア装者との対峙 プレラーティ",
        "code": "SG/W70-074",
        "rarity": "R",
        "expansion": "Senki Zesshou Symphogear AXZ",
        "side": "W",
        "type": "Character",
        "color": "BLUE",
        "level": "0",
        "cost": "0",
        "trigger": [],
        "power": "1000",
        "soul": 1,
        "flavor_text": "-",
        "ability": [
            "【A】When this card is placed on Stage from Hand, if your Memory has 2 or less cards, you may choose 1 choose 1 「シンフォギア装者との対峙 プレラーティ」 from your Waiting Room, send it to Memory.",
            "【S】CONCENTRATION ［(1) REST this card］ Flip the top 4 cards of your Deck, place them into Waiting Room. For each Climax among those cards, search your Deck for up to 1 Character with 「サンジェルマン」 or 「カリオストロ」 or 「プレラーティ」 in its name and show it to opponent, add it to Hand, shuffle your Deck afterwards."
        ],
        "attributes": [
            "Alchemy 《錬金術》"
        ],
        "set": "SG",
        "release": "W70",
        "sid": "074",
        "image": "https://images.littleakiba.com/tcg/card53329-large.jpg"
    },
    {
        "name": "繋ぐ力 翼",
        "code": "SG/W70-075",
        "rarity": "R",
        "expansion": "Senki Zesshou Symphogear AXZ",
        "side": "W",
        "type": "Character",
        "color": "BLUE",
        "level": "0",
        "cost": "0",
        "trigger": [],
        "power": "2000",
        "soul": 1,
        "flavor_text": "-",
        "ability": [
            "【A】[Place 1 《音楽》 Character from Hand into Waiting Room] When this card is placed on Stage from Hand, you may pay the cost. If you did, choose 1 「新たな戦い 翼」 or 「終わりなき闘争 調」 from your Waiting Room, return it to Hand.",
            "【A】[(1) Place 1 card from Hand into Waiting Room] When this card is placed on Stage from Hand, you may pay the cost. If you did, search your Deck for up to 1 Character with 「翼」 or 「調」 in its name and show it to opponent, add it to Hand, shuffle your Deck afterwards."
        ],
        "attributes": [
            "Music 《音楽》",
            "Weapon 《武器》"
        ],
        "set": "SG",
        "release": "W70",
        "sid": "075",
        "image": "https://images.littleakiba.com/tcg/card53330-large.jpg"
    },
    {
        "name": "スイカ割り 翼",
        "code": "SG/W70-076",
        "rarity": "R",
        "expansion": "Senki Zesshou Symphogear AXZ",
        "side": "W",
        "type": "Character",
        "color": "BLUE",
        "level": "0",
        "cost": "0",
        "trigger": [],
        "power": "4000",
        "soul": 1,
        "flavor_text": "-",
        "ability": [
            "【C】You cannot play Event and 『ASSIST』 from Hand."
        ],
        "attributes": [
            "Music 《音楽》",
            "Weapon 《武器》"
        ],
        "set": "SG",
        "release": "W70",
        "sid": "076",
        "image": "https://images.littleakiba.com/tcg/card53332-large.jpg"
    },
    {
        "name": "終わりなき闘争 翼",
        "code": "SG/W70-077",
        "rarity": "R",
        "expansion": "Senki Zesshou Symphogear AXZ",
        "side": "W",
        "type": "Character",
        "color": "BLUE",
        "level": "1",
        "cost": "0",
        "trigger": [],
        "power": "4000",
        "soul": 1,
        "flavor_text": "-",
        "ability": [
            "【C】For each of your other 《音楽》 Character, this card gets +500 Power.",
            "【A】When this card attacks, if you have 2 or more other 《音楽》 Character, look at up to 2 cards from your top Deck, choose 1 card, place it on top Deck, place the remaining cards into Waiting Room."
        ],
        "attributes": [
            "Music 《音楽》",
            "Weapon 《武器》"
        ],
        "set": "SG",
        "release": "W70",
        "sid": "077",
        "image": "https://images.littleakiba.com/tcg/card53334-large.jpg"
    },
    {
        "name": "支配からの解放 サンジェルマン",
        "code": "SG/W70-078",
        "rarity": "R",
        "expansion": "Senki Zesshou Symphogear AXZ",
        "side": "W",
        "type": "Character",
        "color": "BLUE",
        "level": "1",
        "cost": "0",
        "trigger": [],
        "power": "5000",
        "soul": 1,
        "flavor_text": "-",
        "ability": [
            "【A】【CXCOMBO】When this card attacks, if 「誰かのために」 is in your Climax Slot, and you have other 《錬金術》 Character, look at up to 4 cards from your top Deck, choose up to 1 Character with 「サンジェルマン」 or 「カリオストロ」 or 「プレラーティ」 in its name and show it to opponent, add it to Hand, place the remaining cards into Waiting Room."
        ],
        "attributes": [
            "Alchemy 《錬金術》"
        ],
        "set": "SG",
        "release": "W70",
        "sid": "078",
        "image": "https://images.littleakiba.com/tcg/card53336-large.jpg"
    },
    {
        "name": "サンジェルマン＆プレラーティ＆カリオストロ",
        "code": "SG/W70-079",
        "rarity": "R",
        "expansion": "Senki Zesshou Symphogear AXZ",
        "side": "W",
        "type": "Character",
        "color": "BLUE",
        "level": "3",
        "cost": "2",
        "trigger": [
            "SOUL"
        ],
        "power": "9000",
        "soul": 2,
        "flavor_text": "-",
        "ability": [
            "【C】If you have 4 or more 《錬金術》 Character, this card gets -1 Level in your Hand.",
            "【C】For each of your other Character with Level 0 or lower at Back Row, this card gets +1000 Power.",
            "【A】When this card is placed on Stage from Hand or by 「シンフォギア装者との対峙 サンジェルマン」 's 【A】 effect, you may place the top card of your Clock into Waiting Room."
        ],
        "attributes": [
            "Alchemy 《錬金術》"
        ],
        "set": "SG",
        "release": "W70",
        "sid": "079",
        "image": "https://images.littleakiba.com/tcg/card53337-large.jpg"
    },
    {
        "name": "シンフォギア装者との対峙 サンジェルマン",
        "code": "SG/W70-080",
        "rarity": "R",
        "expansion": "Senki Zesshou Symphogear AXZ",
        "side": "W",
        "type": "Character",
        "color": "BLUE",
        "level": "3",
        "cost": "2",
        "trigger": [
            "SOUL"
        ],
        "power": "9500",
        "soul": 2,
        "flavor_text": "-",
        "ability": [
            "【C】For each of your other Character with Level 0 or lower at Back Row, this card gets +1000 Power.",
            "【A】[(1)] When this card is placed on Stage from Hand, you may pay the cost. If you did, choose 1 「サンジェルマン＆プレラーティ＆カリオストロ」 from your Waiting Room, place it into any slot on Stage.",
            "【A】【CXCOMBO】RECOLLECTION [(2) Place 1 card from Hand into Waiting Room] This Ability can be activated up to 1 time each turn. When this card's battle opponent becomes REVERSE, if 「理想を追い求める者」 is in your Climax Slot, and your Memory has 2 or more 《錬金術》 Character, you may pay the cost. If you did, STAND this card."
        ],
        "attributes": [
            "Alchemy 《錬金術》"
        ],
        "set": "SG",
        "release": "W70",
        "sid": "080",
        "image": "https://images.littleakiba.com/tcg/card53339-large.jpg"
    },
    {
        "name": "パヴァリア光明結社 サンジェルマン",
        "code": "SG/W70-081",
        "rarity": "U",
        "expansion": "Senki Zesshou Symphogear AXZ",
        "side": "W",
        "type": "Character",
        "color": "BLUE",
        "level": "0",
        "cost": "0",
        "trigger": [],
        "power": "1500",
        "soul": 1,
        "flavor_text": "-",
        "ability": [
            "【A】When this card is placed on Stage from Hand, if you have other 《錬金術》 Character, place 2 cards from your top Deck into Waiting Room. If there is a Climax among those cards, choose 1 of your Character, during this turn, it gets +2000 Power.",
            "【A】[(1) Place the top card of your Deck into Clock] When this card is placed into Waiting Room from Stage, you may pay the cost. If you did, look at up to 3 cards from your top Deck, choose up to 1 Character and show it to opponent, add it to Hand, place the remaining cards into Waiting Room."
        ],
        "attributes": [
            "Alchemy 《錬金術》"
        ],
        "set": "SG",
        "release": "W70",
        "sid": "081",
        "image": "https://images.littleakiba.com/tcg/card53340-large.jpg"
    },
    {
        "name": "それぞれの正義 サンジェルマン",
        "code": "SG/W70-082",
        "rarity": "U",
        "expansion": "Senki Zesshou Symphogear AXZ",
        "side": "W",
        "type": "Character",
        "color": "BLUE",
        "level": "0",
        "cost": "0",
        "trigger": [],
        "power": "2500",
        "soul": 1,
        "flavor_text": "-",
        "ability": [
            "【C】If your Stock has 2 or less cards, this card gets +1500 Power."
        ],
        "attributes": [
            "Alchemy 《錬金術》"
        ],
        "set": "SG",
        "release": "W70",
        "sid": "082",
        "image": "https://images.littleakiba.com/tcg/card53341-large.jpg"
    },
    {
        "name": "譲れない胸の張り合い カリオストロ",
        "code": "SG/W70-083",
        "rarity": "U",
        "expansion": "Senki Zesshou Symphogear AXZ",
        "side": "W",
        "type": "Character",
        "color": "BLUE",
        "level": "1",
        "cost": "0",
        "trigger": [],
        "power": "4500",
        "soul": 1,
        "flavor_text": "-",
        "ability": [
            "【A】When this card is placed on Stage from Hand, reveal the top card of your Deck. If that card is a 《錬金術》 Character, during this turn, this card gets +2000 Power. (Return revealed card to its original position)",
            "【A】When this card is placed into Waiting Room from Stage, you may reveal up to 3 cards from your top Deck. If 1 or more is revealed , choose up to 1 Character with 「サンジェルマン」 or 「カリオストロ」 or 「プレラーティ」 in its name, add it to Hand, place the remaining cards into Waiting Room, choose 1 card from your Hand, place it into Waiting Room."
        ],
        "attributes": [
            "Alchemy 《錬金術》"
        ],
        "set": "SG",
        "release": "W70",
        "sid": "083",
        "image": "https://images.littleakiba.com/tcg/card53342-large.jpg"
    },
    {
        "name": "忠告する翼",
        "code": "SG/W70-084",
        "rarity": "U",
        "expansion": "Senki Zesshou Symphogear AXZ",
        "side": "W",
        "type": "Character",
        "color": "BLUE",
        "level": "1",
        "cost": "1",
        "trigger": [
            "SOUL"
        ],
        "power": "3500",
        "soul": 1,
        "flavor_text": "-",
        "ability": [
            "【C】SUPPORT All your 《音楽》 Character in front of this card gets +X Power. X is equal to that Character's Level x500.",
            "【A】When your Character Trigger Checks a card with Soul Trigger Icon, choose 1 of your Character with 「翼」 or 「調」 in its name, during this turn, it gets +2000 Power."
        ],
        "attributes": [
            "Music 《音楽》",
            "Weapon 《武器》"
        ],
        "set": "SG",
        "release": "W70",
        "sid": "084",
        "image": "https://images.littleakiba.com/tcg/card53343-large.jpg"
    },
    {
        "name": "待機中 カリオストロ",
        "code": "SG/W70-085",
        "rarity": "U",
        "expansion": "Senki Zesshou Symphogear AXZ",
        "side": "W",
        "type": "Character",
        "color": "BLUE",
        "level": "1",
        "cost": "1",
        "trigger": [],
        "power": "5500",
        "soul": 1,
        "flavor_text": "-",
        "ability": [
            "【A】When your other 《錬金術》 Character attacks, during this turn, this card gets +1500 Power.",
            "【A】ENCORE ［Place 1 Character from Hand into Waiting Room］ (When this card is placed into Waiting Room from Stage, you may pay this Cost. If you do, place this card in its previous slot in REST)"
        ],
        "attributes": [
            "Alchemy 《錬金術》"
        ],
        "set": "SG",
        "release": "W70",
        "sid": "085",
        "image": "https://images.littleakiba.com/tcg/card53344-large.jpg"
    },
    {
        "name": "余裕の表情 カリオストロ",
        "code": "SG/W70-086",
        "rarity": "C",
        "expansion": "Senki Zesshou Symphogear AXZ",
        "side": "W",
        "type": "Character",
        "color": "BLUE",
        "level": "0",
        "cost": "0",
        "trigger": [],
        "power": "1500",
        "soul": 1,
        "flavor_text": "-",
        "ability": [
            "【C】During your turn, all your other 「余裕の表情 プレラーティ」 gains the following Ability. 『【C】This card cannot become REVERSE.』",
            "【A】When this card attacks, choose 1 of your 《錬金術》 Character, during this turn, it gets +1 Level and +1000 Power."
        ],
        "attributes": [
            "Alchemy 《錬金術》"
        ],
        "set": "SG",
        "release": "W70",
        "sid": "086",
        "image": "https://images.littleakiba.com/tcg/card53345-large.jpg"
    },
    {
        "name": "バースディ・パーティ 翼",
        "code": "SG/W70-087",
        "rarity": "C",
        "expansion": "Senki Zesshou Symphogear AXZ",
        "side": "W",
        "type": "Character",
        "color": "BLUE",
        "level": "0",
        "cost": "0",
        "trigger": [],
        "power": "2000",
        "soul": 1,
        "flavor_text": "-",
        "ability": [
            "【C】During your turn, your other 《音楽》 Character at the Center Slot of Front Row gets +1000 Power.",
            "【S】[(1) REST this card] Choose 1 of your 「バースディ・パーティ　マリア」, during this turn, it gets +1000 Power, gains the following Ability. 『【A】When this card's battle opponent becomes REVERSE, search your Deck for up to 1 Character with 「翼」 or 「マリア」 in its name and show it to opponent, add it to Hand, shuffle your Deck afterwards.』"
        ],
        "attributes": [
            "Music 《音楽》",
            "Weapon 《武器》"
        ],
        "set": "SG",
        "release": "W70",
        "sid": "087",
        "image": "https://images.littleakiba.com/tcg/card53346-large.jpg"
    },
    {
        "name": "S.O.N.G.への情報提供 サンジェルマン",
        "code": "SG/W70-088",
        "rarity": "C",
        "expansion": "Senki Zesshou Symphogear AXZ",
        "side": "W",
        "type": "Character",
        "color": "BLUE",
        "level": "0",
        "cost": "0",
        "trigger": [],
        "power": "2500",
        "soul": 1,
        "flavor_text": "-",
        "ability": [
            "【S】[(1) Place this card into Waiting Room] Choose 1 「最後の歌」 from your Waiting Room, return it to Hand."
        ],
        "attributes": [
            "Alchemy 《錬金術》"
        ],
        "set": "SG",
        "release": "W70",
        "sid": "088",
        "image": "https://images.littleakiba.com/tcg/card53347-large.jpg"
    },
    {
        "name": "LiNKER完成のために エルフナイン",
        "code": "SG/W70-089",
        "rarity": "C",
        "expansion": "Senki Zesshou Symphogear AXZ",
        "side": "W",
        "type": "Character",
        "color": "BLUE",
        "level": "0",
        "cost": "0",
        "trigger": [],
        "power": "2500",
        "soul": 1,
        "flavor_text": "-",
        "ability": [
            "【A】When this card becomes REVERSE, you may reveal up to 3 cards from your top Deck. If 1 or more is revealed, choose up to 1 Character with 「マリア」 or 「切歌」 or 「調」 in its name among those cards, add it to Hand, place the remaining cards into Waiting Room, choose 1 card from your Hand, place it into Waiting Room."
        ],
        "attributes": [
            "Alchemy 《錬金術》"
        ],
        "set": "SG",
        "release": "W70",
        "sid": "089",
        "image": "https://images.littleakiba.com/tcg/card53348-large.jpg"
    },
    {
        "name": "余裕の表情 プレラーティ",
        "code": "SG/W70-090",
        "rarity": "C",
        "expansion": "Senki Zesshou Symphogear AXZ",
        "side": "W",
        "type": "Character",
        "color": "BLUE",
        "level": "0",
        "cost": "0",
        "trigger": [
            "CHOICE"
        ],
        "power": "3000",
        "soul": 0,
        "flavor_text": "-",
        "ability": [
            ""
        ],
        "attributes": [],
        "set": "SG",
        "release": "W70",
        "sid": "090",
        "image": "https://images.littleakiba.com/tcg/card53349-large.jpg"
    },
    {
        "name": "疾駆するプレラーティ",
        "code": "SG/W70-091",
        "rarity": "C",
        "expansion": "Senki Zesshou Symphogear AXZ",
        "side": "W",
        "type": "Character",
        "color": "BLUE",
        "level": "1",
        "cost": "0",
        "trigger": [],
        "power": "2500",
        "soul": 1,
        "flavor_text": "-",
        "ability": [
            "【C】RECOLLECTION If 「シンフォギア装者との対峙 カリオストロ」 is in your Memory, this card gets +4000 Power.",
            "【A】RECOLLECTION When this card is placed on Stage from Hand, if 「シンフォギア装者との対峙 プレラーティ」 is in your Memory, you may draw 1 card. If you did, choose 1 card from your Hand, place it into Waiting Room."
        ],
        "attributes": [
            "Alchemy 《錬金術》"
        ],
        "set": "SG",
        "release": "W70",
        "sid": "091",
        "image": "https://images.littleakiba.com/tcg/card53350-large.jpg"
    },
    {
        "name": "パヴァリア光明結社 プレラーティ",
        "code": "SG/W70-092",
        "rarity": "C",
        "expansion": "Senki Zesshou Symphogear AXZ",
        "side": "W",
        "type": "Character",
        "color": "BLUE",
        "level": "1",
        "cost": "0",
        "trigger": [],
        "power": "5000",
        "soul": 1,
        "flavor_text": "-",
        "ability": [
            "【A】When this card is placed on Stage from Hand, during this turn, this card gets +X Power. X is equal to the number of your 《錬金術》 Character x500."
        ],
        "attributes": [
            "Alchemy 《錬金術》"
        ],
        "set": "SG",
        "release": "W70",
        "sid": "092",
        "image": "https://images.littleakiba.com/tcg/card53351-large.jpg"
    },
    {
        "name": "一網打尽 翼",
        "code": "SG/W70-093",
        "rarity": "C",
        "expansion": "Senki Zesshou Symphogear AXZ",
        "side": "W",
        "type": "Character",
        "color": "BLUE",
        "level": "1",
        "cost": "1",
        "trigger": [],
        "power": "3000",
        "soul": 1,
        "flavor_text": "-",
        "ability": [
            "【C】During your turn, this card gets +3000 Power.",
            "【C】If the Character facing this card is Cost 0 or lower, this card cannot become REVERSE."
        ],
        "attributes": [
            "Music 《音楽》",
            "Weapon 《武器》"
        ],
        "set": "SG",
        "release": "W70",
        "sid": "093",
        "image": "https://images.littleakiba.com/tcg/card53352-large.jpg"
    },
    {
        "name": "不信感 プレラーティ",
        "code": "SG/W70-094",
        "rarity": "C",
        "expansion": "Senki Zesshou Symphogear AXZ",
        "side": "W",
        "type": "Character",
        "color": "BLUE",
        "level": "2",
        "cost": "1",
        "trigger": [
            "SOUL"
        ],
        "power": "1500",
        "soul": 1,
        "flavor_text": "-",
        "ability": [
            "【A】When you use this card's 『ASSIST』, place 3 cards from your top Deck into Waiting Room.",
            "【S】【COUNTER】 ASSIST 3000 Level 2 ［(1) Place this card from Hand into Waiting Room］ (Choose 1 of your Characters being Front Attacked, during that turn, it gets ＋3000 Power)"
        ],
        "attributes": [
            "Alchemy 《錬金術》"
        ],
        "set": "SG",
        "release": "W70",
        "sid": "094",
        "image": "https://images.littleakiba.com/tcg/card53353-large.jpg"
    },
    {
        "name": "パヴァリア光明結社 カリオストロ",
        "code": "SG/W70-095",
        "rarity": "C",
        "expansion": "Senki Zesshou Symphogear AXZ",
        "side": "W",
        "type": "Character",
        "color": "BLUE",
        "level": "2",
        "cost": "1",
        "trigger": [
            "SOUL"
        ],
        "power": "6000",
        "soul": 1,
        "flavor_text": "-",
        "ability": [
            "【A】When this card is placed on Stage from Hand, choose 1 of your other 《錬金術》 Character, during this turn, it gets +1000 Power.",
            "【A】When this card becomes REVERSE, if this card's battle opponent's Level is higher than opponent's Level, you may place that Character to bottom Deck."
        ],
        "attributes": [
            "Alchemy 《錬金術》"
        ],
        "set": "SG",
        "release": "W70",
        "sid": "095",
        "image": "https://images.littleakiba.com/tcg/card53354-large.jpg"
    },
    {
        "name": "絆のユニゾン 翼",
        "code": "SG/W70-096",
        "rarity": "C",
        "expansion": "Senki Zesshou Symphogear AXZ",
        "side": "W",
        "type": "Character",
        "color": "BLUE",
        "level": "2",
        "cost": "1",
        "trigger": [
            "SOUL"
        ],
        "power": "7500",
        "soul": 1,
        "flavor_text": "-",
        "ability": [
            "【A】When this card attacks, during this turn, this card gets +X Power. X is equal to the number of your other 《音楽》 Character x500.",
            "【A】【CXCOMBO】[(1)] When this card attacks, if 「風月ノ疾双」 is in your Climax Slot, you may pay the cost. If you did, deal 1 Damage to opponent. (Damage can be cancelled)"
        ],
        "attributes": [
            "Music 《音楽》",
            "Weapon 《武器》"
        ],
        "set": "SG",
        "release": "W70",
        "sid": "096",
        "image": "https://images.littleakiba.com/tcg/card53355-large.jpg"
    },
    {
        "name": "最後の歌",
        "code": "SG/W70-097",
        "rarity": "U",
        "expansion": "Senki Zesshou Symphogear AXZ",
        "side": "W",
        "type": "Event",
        "color": "BLUE",
        "level": "3",
        "cost": "1",
        "trigger": [],
        "power": "N/A",
        "soul": 0,
        "flavor_text": "-",
        "ability": [
            "Look at up to 4 cards from your top Deck, choose up to 1 《錬金術》 Character and show it to opponent, add it to Hand, place the remaining cards into Waiting Room, choose up to 1 opponent's Character, return it to Hand, choose 1 of your Character, during this turn, it gets +2000 Power."
        ],
        "attributes": [],
        "set": "SG",
        "release": "W70",
        "sid": "097",
        "image": "https://images.littleakiba.com/tcg/card53356-large.jpg"
    },
    {
        "name": "逆羅刹",
        "code": "SG/W70-098",
        "rarity": "CR",
        "expansion": "Senki Zesshou Symphogear AXZ",
        "side": "W",
        "type": "Climax",
        "color": "BLUE",
        "level": "0",
        "cost": "0",
        "trigger": [
            "SOUL",
            "GATE"
        ],
        "power": "N/A",
        "soul": 0,
        "flavor_text": "-",
        "ability": [
            "【C】 All your Characters get +1000 Power, +1 Soul.",
            "(Arch：When this card is triggered, choose 1 Climax from your Waiting Room, you may return it to Hand)"
        ],
        "attributes": [],
        "set": "SG",
        "release": "W70",
        "sid": "098",
        "image": "https://images.littleakiba.com/tcg/card53357-large.jpg"
    },
    {
        "name": "誰かのために",
        "code": "SG/W70-099",
        "rarity": "CC",
        "expansion": "Senki Zesshou Symphogear AXZ",
        "side": "W",
        "type": "Climax",
        "color": "BLUE",
        "level": "0",
        "cost": "0",
        "trigger": [
            "DRAW"
        ],
        "power": "N/A",
        "soul": 0,
        "flavor_text": "-",
        "ability": [
            "【C】 All your Characters get +1000 Power, +1 Soul.",
            "(Book：When this card is triggered, you may draw 1 card)"
        ],
        "attributes": [],
        "set": "SG",
        "release": "W70",
        "sid": "099",
        "image": "https://images.littleakiba.com/tcg/card53359-large.jpg"
    },
    {
        "name": "理想を追い求める者",
        "code": "SG/W70-100",
        "rarity": "CC",
        "expansion": "Senki Zesshou Symphogear AXZ",
        "side": "W",
        "type": "Climax",
        "color": "BLUE",
        "level": "0",
        "cost": "0",
        "trigger": [
            "SOUL",
            "GATE"
        ],
        "power": "N/A",
        "soul": 0,
        "flavor_text": "-",
        "ability": [
            "【C】 All your Characters get +1000 Power, +1 Soul.",
            "(Arch：When this card is triggered, choose 1 Climax from your Waiting Room, you may return it to Hand)"
        ],
        "attributes": [],
        "set": "SG",
        "release": "W70",
        "sid": "100",
        "image": "https://images.littleakiba.com/tcg/card53360-large.jpg"
    },
    {
        "name": "連携攻撃 響",
        "code": "SG/W70-101",
        "rarity": "PR",
        "expansion": "Senki Zesshou Symphogear AXZ",
        "side": "W",
        "type": "Character",
        "color": "YELLOW",
        "level": "1",
        "cost": "0",
        "trigger": [],
        "power": "3500",
        "soul": 1,
        "flavor_text": "-",
        "ability": [
            "【A】When this card becomes REVERSE, if this card's battle opponent is Cost 0 or lower, you may place that Character into Stock.If you did, place opponent's bottom Stock into Waiting Room."
        ],
        "attributes": [
            "Music 《音楽》"
        ],
        "set": "SG",
        "release": "W70",
        "sid": "101",
        "image": "https://images.littleakiba.com/tcg/card53362-large.jpg"
    },
    {
        "name": "無茶な訓練 切歌",
        "code": "SG/W70-102",
        "rarity": "PR",
        "expansion": "Senki Zesshou Symphogear AXZ",
        "side": "W",
        "type": "Character",
        "color": "GREEN",
        "level": "1",
        "cost": "1",
        "trigger": [],
        "power": "6000",
        "soul": 1,
        "flavor_text": "-",
        "ability": [
            "【C】If you have other 「無茶な訓練 調」, this card gets +1000 Power.",
            "【A】ENCORE ［Place the top card of your Deck into Clock］ (When this card is placed into Waiting Room from Stage, you may pay this Cost. If you do, place this card in its previous slot in REST)"
        ],
        "attributes": [
            "Music 《音楽》",
            "Weapon 《武器》"
        ],
        "set": "SG",
        "release": "W70",
        "sid": "102",
        "image": "https://images.littleakiba.com/tcg/card53363-large.jpg"
    },
    {
        "name": "無茶な訓練 調",
        "code": "SG/W70-103",
        "rarity": "PR",
        "expansion": "Senki Zesshou Symphogear AXZ",
        "side": "W",
        "type": "Character",
        "color": "GREEN",
        "level": "1",
        "cost": "0",
        "trigger": [],
        "power": "5000",
        "soul": 1,
        "flavor_text": "-",
        "ability": [
            "【A】At the beginning of opponent's Attack Phase, you may choose 1 of your 「無茶な訓練 切歌」 and this card, STAND and exchange them."
        ],
        "attributes": [
            "Music 《音楽》",
            "Weapon 《武器》"
        ],
        "set": "SG",
        "release": "W70",
        "sid": "103",
        "image": "https://images.littleakiba.com/tcg/card53364-large.jpg"
    },
    {
        "name": "亜空間の檻の中で クリス",
        "code": "SG/W70-104",
        "rarity": "PR",
        "expansion": "Senki Zesshou Symphogear AXZ",
        "side": "W",
        "type": "Character",
        "color": "RED",
        "level": "3",
        "cost": "2",
        "trigger": [
            "SOUL"
        ],
        "power": "9500",
        "soul": 2,
        "flavor_text": "-",
        "ability": [
            "【C】If you have 4 or more 《音楽》 Character, this card gets -1 Level in your Hand.",
            "【A】When this card is placed on Stage from Hand, you draw up to 1 card, during this turn, this card gets +2000 Power."
        ],
        "attributes": [
            "Music 《音楽》",
            "Weapon 《武器》"
        ],
        "set": "SG",
        "release": "W70",
        "sid": "104",
        "image": "https://images.littleakiba.com/tcg/card53365-large.jpg"
    },
    {
        "name": "あきらめない心 マリア",
        "code": "SG/W70-105",
        "rarity": "PR",
        "expansion": "Senki Zesshou Symphogear AXZ",
        "side": "W",
        "type": "Character",
        "color": "RED",
        "level": "2",
        "cost": "2",
        "trigger": [
            "SOUL"
        ],
        "power": "9000",
        "soul": 2,
        "flavor_text": "-",
        "ability": [
            "【C】This card cannot Side Attack.",
            "【A】[(1)] At the beginning of Encore Step, if you have no other REST Character at Front Row, you may pay the cost. If you did, REST this card."
        ],
        "attributes": [
            "Music 《音楽》",
            "Weapon 《武器》"
        ],
        "set": "SG",
        "release": "W70",
        "sid": "105",
        "image": "https://images.littleakiba.com/tcg/card53366-large.jpg"
    },
    {
        "name": "連携攻撃 翼",
        "code": "SG/W70-106",
        "rarity": "PR",
        "expansion": "Senki Zesshou Symphogear AXZ",
        "side": "W",
        "type": "Character",
        "color": "BLUE",
        "level": "0",
        "cost": "0",
        "trigger": [],
        "power": "1500",
        "soul": 1,
        "flavor_text": "-",
        "ability": [
            "【A】When this card is placed on Stage from Hand, during this turn, this card gets +1500 Power.",
            "【A】When this card attacks, reveal the top card of your Deck. If that card is a 《音楽》 Character, add it to Hand, choose 1 card from your Hand, place it into Waiting Room. (If not, return revealed card to its original position)"
        ],
        "attributes": [
            "Music 《音楽》",
            "Weapon 《武器》"
        ],
        "set": "SG",
        "release": "W70",
        "sid": "106",
        "image": "https://images.littleakiba.com/tcg/card53367-large.jpg"
    },
    {
        "name": "“アンリミ”調",
        "code": "SG/W72-128",
        "rarity": "PR",
        "expansion": "Senki Zesshou Symphogear AXZ",
        "side": "W",
        "type": "Character",
        "color": "GREEN",
        "level": "0",
        "cost": "0",
        "trigger": [],
        "power": "2500",
        "soul": 1,
        "flavor_text": "-",
        "ability": [
            ""
        ],
        "attributes": [
            "Music 《音楽》",
            "Weapon 《武器》"
        ],
        "set": "SG",
        "release": "W72",
        "sid": "128",
        "image": "https://images.littleakiba.com/tcg/card55049-large.jpg"
    }
]